PyLUCCBA/__init__.py
PyLUCCBA/core.py
PyLUCCBA/tools.py
PyLUCCBA/examples/__init__.py
PyLUCCBA/examples/studies_constant_settings.py
PyLUCCBA/examples/study_Grassland_CarbonPriceEffect.py
PyLUCCBA/examples/study_Grassland_CombinedEffect.py
PyLUCCBA/examples/study_Grassland_CompensatoryRate.py
PyLUCCBA/examples/study_Grassland_DiscountingEffect.py
PyLUCCBA/examples/study_Grassland_PaybackPeriod.py
PyLUCCBA/examples/study_demo.py
PyLUCCBA/examples/Example-1/FLOWS HA land [WHEAT].png
PyLUCCBA/examples/Example-1/FLOWS TONNES ETH [O].png
PyLUCCBA/examples/Example-1/FLOWS TONNES OIL [O].png
PyLUCCBA/examples/Example-1/FLOWS TONNES carbon so [diff-IMPROVED GRASSLAND~WHEAT].png
PyLUCCBA/examples/Example-1/FLOWS TONNES carbon so [unif-IMPROVED GRASSLAND~WHEAT].png
PyLUCCBA/examples/Example-1/FLOWS TONNES carbon u-so [diff-IMPROVED GRASSLAND~WHEAT].png
PyLUCCBA/examples/Example-1/FLOWS TONNES carbon u-so [unif-IMPROVED GRASSLAND~WHEAT].png
PyLUCCBA/examples/Example-1/FLOWS TONNES carbon vg [diff-IMPROVED GRASSLAND~WHEAT].png
PyLUCCBA/examples/Example-1/FLOWS TONNES carbon vg [unif-IMPROVED GRASSLAND~WHEAT].png
PyLUCCBA/examples/Example-1/FLOWS TONNES carbon vg+so [diff-IMPROVED GRASSLAND~WHEAT].png
PyLUCCBA/examples/Example-1/FLOWS TONNES carbon vg+so [unif-IMPROVED GRASSLAND~WHEAT].png
PyLUCCBA/examples/Example-1/FLOWS TONNES co2 so [diff-IMPROVED GRASSLAND~WHEAT].png
PyLUCCBA/examples/Example-1/FLOWS TONNES co2 so [unif-IMPROVED GRASSLAND~WHEAT].png
PyLUCCBA/examples/Example-1/FLOWS TONNES co2 total [OIL].png
PyLUCCBA/examples/Example-1/FLOWS TONNES co2 total [diff-ETH].png
PyLUCCBA/examples/Example-1/FLOWS TONNES co2 total [unif-ETH].png
PyLUCCBA/examples/Example-1/FLOWS TONNES co2 vg [diff-IMPROVED GRASSLAND~WHEAT].png
PyLUCCBA/examples/Example-1/FLOWS TONNES co2 vg [unif-IMPROVED GRASSLAND~WHEAT].png
PyLUCCBA/examples/Example-1/FLOWS TONNES co2 vg+so [diff-IMPROVED GRASSLAND~WHEAT].png
PyLUCCBA-0.9.23.dist-info/LICENSE
PyLUCCBA-0.9.23.dist-info/METADATA
PyLUCCBA-0.9.23.dist-info/WHEEL
PyLUCCBA-0.9.23.dist-info/top_level.txt
PyLUCCBA-0.9.23.dist-info/RECORD
