Metadata-Version: 2.1
Name: PyLUCCBA
Version: 0.9.23
Summary: A Land-Use-Change Cost-Benefit-Analysis calculator coded in Python27&3, PyLUCCBA.
Home-page: https://github.com/lfaucheux/PyLUCCBA
Author: Laurent Faucheux
Author-email: laurent.faucheux@hotmail.fr
License: MIT
Download-URL: https://github.com/lfaucheux/PyLUCCBA/archive/0.9.23.tar.gz
Keywords: land use change,cost benefit analysis,environmental economics
Platform: UNKNOWN
Classifier: Programming Language :: Python :: 2.7
Classifier: Programming Language :: Python :: 3
Classifier: Intended Audience :: Developers
Classifier: Intended Audience :: Science/Research
Classifier: Topic :: Scientific/Engineering
Requires-Dist: numpy (>=1.14.0)
Requires-Dist: scipy (>=1.0.0)
Requires-Dist: openpyxl (>=2.5.5)
Requires-Dist: matplotlib (>=1.4.3)
